pgsdk/__init__.py
pgsdk-0.0.2.dist-info/METADATA
pgsdk-0.0.2.dist-info/WHEEL
pgsdk-0.0.2.dist-info/top_level.txt
pgsdk-0.0.2.dist-info/RECORD
