Metadata-Version: 2.1
Name: pgsdk
Version: 0.0.2
Summary: pgsdk is the Python SDK for Paralegal Genius
Author: Josh XT
Author-email: josh@devxt.com
Requires-Python: >=3.10
Requires-Dist: requests
Requires-Dist: pyotp
